flask_hot_reload/__init__.py
flask_hot_reload/core.py
flask_hot_reload-0.3.0.dist-info/METADATA
flask_hot_reload-0.3.0.dist-info/WHEEL
flask_hot_reload-0.3.0.dist-info/top_level.txt
flask_hot_reload-0.3.0.dist-info/RECORD
