Metadata-Version: 2.2
Name: flask-hot-reload
Version: 0.3.0
Summary: A Flask extension that provides real-time hot reload for templates, static files and Python code changes
Home-page: https://github.com/ZhouYu2156/flask-hot-reload
Author: Blake Zhou
Author-email: 1043744584@qq.com
Project-URL: Documentation, https://github.com/ZhouYu2156/flask-hot-reload#readme
Project-URL: Bug Reports, https://github.com/ZhouYu2156/flask-hot-reload/issues
Project-URL: Source Code, https://github.com/ZhouYu2156/flask-hot-reload
Keywords: flask hot reload live reload development tools web hmr
Classifier: Development Status :: 4 - Beta
Classifier: Environment :: Web Environment
Classifier: Framework :: Flask
Classifier: Intended Audience :: Developers
Classifier: License :: OSI Approved :: MIT License
Classifier: Operating System :: OS Independent
Classifier: Programming Language :: Python :: 3
Classifier: Programming Language :: Python :: 3.7
Classifier: Programming Language :: Python :: 3.8
Classifier: Programming Language :: Python :: 3.9
Classifier: Programming Language :: Python :: 3.10
Classifier: Programming Language :: Python :: 3.11
Classifier: Programming Language :: Python :: 3.12
Classifier: Topic :: Internet :: WWW/HTTP :: Dynamic Content
Classifier: Topic :: Software Development :: Libraries :: Python Modules
Classifier: Topic :: Software Development :: Build Tools
Requires-Python: >=3.7
Requires-Dist: Flask>=2.0.0
Requires-Dist: flask-sock>=0.4.0
Requires-Dist: watchdog>=2.1.0
Requires-Dist: colorama>=0.4.6
Dynamic: author
Dynamic: author-email
Dynamic: classifier
Dynamic: description
Dynamic: description-content-type
Dynamic: home-page
Dynamic: keywords
Dynamic: project-url
Dynamic: requires-dist
Dynamic: requires-python
Dynamic: summary
